video_annotator/README.md
video_annotator/__init__.py
video_annotator/frontend/.gitignore
video_annotator/frontend/__init__.py
video_annotator/frontend/build/667.c19604e75e7683f31472.js
video_annotator/frontend/build/667.c19604e75e7683f31472.js.LICENSE.txt
video_annotator/frontend/build/__init__.py
video_annotator/frontend/build/index.html
video_annotator/frontend/build/main.cbb3d1aa43952f4a24f4.js
video_annotator/frontend/build/runtime.d142a4db2049c10a1bea.js
video_annotator/frontend/package-lock.json
video_annotator/frontend/package.json
video_annotator/frontend/public/index.html
video_annotator/frontend/src/VideoAnnotator.css
video_annotator/frontend/src/VideoAnnotator.tsx
video_annotator/frontend/src/index.tsx
video_annotator/frontend/src/types.ts
video_annotator/frontend/tsconfig.json
video_annotator/frontend/webpack.config.js
video_annotator/video_annotator.py
streamlit_video_annotator-0.1.3.dist-info/WHEEL
streamlit_video_annotator-0.1.3.dist-info/METADATA
streamlit_video_annotator-0.1.3.dist-info/RECORD
