Metadata-Version: 2.4
Name: streamlit-video-annotator
Version: 0.1.3
Summary: A Streamlit component for annotating videos with drawable regions and time-range markers
Keywords: streamlit,video,annotation,machine-learning,computer-vision
Author: Mikael Nystrom
Author-email: Mikael Nystrom <mikaelnystromm@gmail.com>
License-Expression: MIT
Classifier: Development Status :: 3 - Alpha
Classifier: Intended Audience :: Developers
Classifier: Intended Audience :: Science/Research
Classifier: Topic :: Scientific/Engineering :: Artificial Intelligence
Classifier: Topic :: Multimedia :: Video
Classifier: Programming Language :: Python :: 3
Classifier: Programming Language :: Python :: 3.8
Classifier: Programming Language :: Python :: 3.9
Classifier: Programming Language :: Python :: 3.10
Classifier: Programming Language :: Python :: 3.11
Classifier: Programming Language :: Python :: 3.12
Classifier: Operating System :: OS Independent
Requires-Dist: streamlit>=1.0.0
Requires-Python: >=3.8
Project-URL: Homepage, https://github.com/mikaelnystroms/video_annotator
Project-URL: Repository, https://github.com/mikaelnystroms/video_annotator
Project-URL: Issues, https://github.com/mikaelnystroms/video_annotator/issues
